mbiter/__init__.py
mbiter/deque.py
mbiter/execute.py
mbiter-0.1.2.dist-info/METADATA
mbiter-0.1.2.dist-info/WHEEL
mbiter-0.1.2.dist-info/entry_points.txt
mbiter-0.1.2.dist-info/top_level.txt
mbiter-0.1.2.dist-info/RECORD
