Metadata-Version: 2.2
Name: mbiter
Version: 0.1.2
Summary: Add your description here
Author-email: Sebastian <peraltas@seas.upenn.edu>
Requires-Python: >=3.10
Requires-Dist: rich-click>=1.8.5
Requires-Dist: rich>=13.9.4
